ucbshift/__init__.py
ucbshift/app.py
ucbshift/wsgi.py
ucbshift/apps/__init__.py
ucbshift/apps/display.py
ucbshift/apps/index.py
ucbshift/assets/__init__.py
ucbshift/assets/favicon.ico
ucbshift/assets/style.css
ucbshift/data_processing/__init__.py
ucbshift/data_processing/data_aug.py
ucbshift/data_processing/density_gen.py
ucbshift/data_processing/display_utils.py
ucbshift/data_processing/json_to_numpy.py
ucbshift/data_processing/xyz_to_json.py
ucbshift/display_utils/__init__.py
ucbshift/display_utils/display_utils.py
ucbshift/display_utils/model_utils.py
ucbshift/display_utils/visualizations.py
ucbshift/test/__init__.py
ucbshift/test/test_3d_densenet.py
ucbshift/test/test_webapp_setup.py
ucbshift/webapp_setup/__init__.py
ucbshift/webapp_setup/download_models.py
ucbshift/webapp_setup/manage_data_folders.py
ucbshift-0.2.data/scripts/ucbshift
ucbshift-0.2.data/scripts/ucbshift_setup
ucbshift-0.2.dist-info/LICENSE
ucbshift-0.2.dist-info/METADATA
ucbshift-0.2.dist-info/WHEEL
ucbshift-0.2.dist-info/top_level.txt
ucbshift-0.2.dist-info/RECORD
