Metadata-Version: 2.1
Name: ucbshift
Version: 0.2
Summary: UCBShift is a tool for predicting and visualizing chemical shifts of molecules.
Home-page: UNKNOWN
Author: Matthew Nemeth
Author-email: mnemeth6@berkeley.edu
License: UNKNOWN
Project-URL: Source, https://github.com/THGLab/ucbshift
Keywords: ucbshift webapp dash
Platform: UNKNOWN
Classifier: License :: OSI Approved :: MIT License
Classifier: Programming Language :: Python :: 3.6
Classifier: Programming Language :: Python :: 3.7
Requires-Python: >=3.6
Requires-Dist: ase
Requires-Dist: dash
Requires-Dist: dash-bio
Requires-Dist: dash-daq
Requires-Dist: dash-table
Requires-Dist: dash-core-components
Requires-Dist: dash-html-components
Requires-Dist: gunicorn
Requires-Dist: keras (==2.4.0)
Requires-Dist: numpy
Requires-Dist: pandas
Requires-Dist: plotly
Requires-Dist: scipy (==1.4.1)
Requires-Dist: tensorflow (==2.2)
Requires-Dist: torch
Requires-Dist: pytest
Requires-Dist: pytest-timeout
